corenlp_dtree_visualizer/__init__.py
corenlp_dtree_visualizer/converters.py
corenlp_vdep-0.1.0.dist-info/LICENSE
corenlp_vdep-0.1.0.dist-info/METADATA
corenlp_vdep-0.1.0.dist-info/WHEEL
corenlp_vdep-0.1.0.dist-info/top_level.txt
corenlp_vdep-0.1.0.dist-info/RECORD
