Metadata-Version: 2.1
Name: corenlp-vdep
Version: 0.1.0
Summary: A dependency tree visualizer for Stanford CoreNLP
Home-page: https://github.com/doug919/corenlp_dtree_visualizer
Author: doug919
Author-email: doug919@gmail.com
License: UNKNOWN
Platform: UNKNOWN
Classifier: Programming Language :: Python :: 3
Classifier: License :: OSI Approved :: MIT License
Classifier: Operating System :: OS Independent
Requires-Python: >=3.6
